nyctrains/__init__.py
nyctrains/_version.py
nyctrains/data_loader.py
nyctrains/main.py
nyctrains/models.py
nyctrains/mta_client.py
nyctrains/static_gtfs.py
nyctrains-1.5.0.post0.dist-info/licenses/LICENSE
nyctrains-1.5.0.post0.dist-info/METADATA
nyctrains-1.5.0.post0.dist-info/WHEEL
nyctrains-1.5.0.post0.dist-info/top_level.txt
nyctrains-1.5.0.post0.dist-info/RECORD
