Metadata-Version: 2.4
Name: nyctrains
Version: 1.5.0.post0
Summary: Python tools and FastAPI backend for MTA GTFS-RT subway and LIRR data
Author-email: Mikael Moise <mikaelmoise00@gmail.com>
Project-URL: Repository, https://github.com/arrismo/nyctrains
Project-URL: Bug Tracker, https://github.com/arrismo/nyctrains/issues
Keywords: data,trains,data science,data engineering,api
Classifier: Development Status :: 5 - Production/Stable
Classifier: License :: OSI Approved :: MIT License
Classifier: Programming Language :: Python
Classifier: Programming Language :: Python :: 3
Classifier: Programming Language :: Python :: 3.10
Classifier: Programming Language :: Python :: 3.11
Classifier: Programming Language :: Python :: 3.12
Classifier: Operating System :: OS Independent
Classifier: Topic :: Scientific/Engineering
Requires-Python: >=3.10
License-File: LICENSE
Requires-Dist: fastapi
Requires-Dist: gtfs-realtime-bindings
Requires-Dist: httpx
Requires-Dist: yc-protobuf3-to-dict
Requires-Dist: pydantic
Requires-Dist: python-dotenv
Requires-Dist: requests
Requires-Dist: uvicorn
Requires-Dist: protobuf
Requires-Dist: pandas
Provides-Extra: test
Requires-Dist: pytest>=8.3.5; extra == "test"
Requires-Dist: pytest-cov; extra == "test"
Requires-Dist: pytest-asyncio; extra == "test"
Requires-Dist: respx; extra == "test"
Dynamic: license-file
